eng_text_cleaner
